COPYING
COPYING.LESSER
LICENSE
MANIFEST.in
README.md
environment.yml
pyproject.toml
requirements.txt
setup.py
docs/description.md
lensmc/INFO
lensmc/__init__.py
lensmc/flags.py
lensmc/image.py
lensmc/likelihood.py
lensmc/measure_shear.py
lensmc/measure_shear_all.py
lensmc/models.py
lensmc/optimise.py
lensmc/prior.py
lensmc/psf.py
lensmc/segmentation.py
lensmc/shear_bias.py
lensmc/shear_utils.py
lensmc/stats.py
lensmc/utils.py
lensmc.egg-info/PKG-INFO
lensmc.egg-info/SOURCES.txt
lensmc.egg-info/dependency_links.txt
lensmc.egg-info/not-zip-safe
lensmc.egg-info/requires.txt
lensmc.egg-info/top_level.txt
lensmc/aux/cache_1x.bin
lensmc/aux/cache_3x.bin
lensmc/aux/cache_5x.bin
lensmc/aux/cache_7x.bin
lensmc/aux/se++.config
lensmc/aux/se.config
lensmc/aux/se.param
lensmc/aux/seg_filter.conv
lensmc/aux/swarp.config
lensmc/src/c/fast_fourier_model.cpp
lensmc/src/c/fast_fourier_model.hpp
lensmc/src/cython/cross_product.c
lensmc/src/cython/cross_product.pyx
lensmc/src/cython/galaxy_model.cpp
lensmc/src/cython/galaxy_model.pxd
lensmc/src/cython/galaxy_model.pyx
lensmc/src/cython/linear_fit.c
lensmc/src/cython/linear_fit.pyx
lensmc/src/cython/star_model.cpp
lensmc/src/cython/star_model.pxd
lensmc/src/cython/star_model.pyx
lensmc/tests/__init__.py
lensmc/tests/test_background.py
lensmc/tests/test_galaxy_runtime.py
lensmc/tests/test_measure_shear.py
lensmc/tests/test_measure_shear_all.py