Metadata-Version: 2.2
Name: lensmc
Version: 25.1
Summary: Python package for weak lensing shear measurements
Home-page: https://gitlab.com/lensmc/LensMC
Author: Giuseppe Congedo
Author-email: giuseppe.congedo@ed.ac.uk
License: LGPL - Copyright (C) 2015 Giuseppe Congedo, University of Edinburgh on behalf of the Euclid Science Ground Segment
Classifier: Development Status :: 4 - Beta
Classifier: Intended Audience :: Science/Research
Classifier: License :: OSI Approved :: GNU Lesser General Public License v3 or later (LGPLv3+)
Classifier: Operating System :: POSIX :: Linux
Classifier: Programming Language :: Python :: 3.1
Classifier: Programming Language :: C++
Classifier: Topic :: Scientific/Engineering :: Astronomy
License-File: LICENSE
License-File: COPYING
License-File: COPYING.LESSER
Requires-Dist: numpy>=1.23.5
Requires-Dist: scipy>=1.10.1
Requires-Dist: astropy>=5.2.1
Requires-Dist: pyfftw>=0.12.0
Dynamic: author
Dynamic: author-email
Dynamic: classifier
Dynamic: description
Dynamic: description-content-type
Dynamic: home-page
Dynamic: license
Dynamic: requires-dist
Dynamic: summary
